dvpio/__init__.py
dvpio/_utils.py
dvpio/read/__init__.py
dvpio/read/image/__init__.py
dvpio/read/image/_metadata.py
dvpio/read/image/_utils.py
dvpio/read/image/custom.py
dvpio/read/image/czi.py
dvpio/read/image/openslide.py
dvpio/read/omics/__init__.py
dvpio/read/omics/_anndata.py
dvpio/read/omics/report_reader.py
dvpio/read/shapes/__init__.py
dvpio/read/shapes/geometry.py
dvpio/read/shapes/lmd_reader.py
dvpio/write/__init__.py
dvpio/write/lmd_writer.py
dvp_io-0.4.1.dist-info/METADATA
dvp_io-0.4.1.dist-info/WHEEL
dvp_io-0.4.1.dist-info/licenses/LICENSE
dvp_io-0.4.1.dist-info/RECORD
