Metadata-Version: 2.4
Name: dvp-io
Version: 0.4.1
Summary: Read and write funtionalities from and to spatialdata for deep visual proteomics
Project-URL: Documentation, https://dvp-io.readthedocs.io/
Project-URL: Homepage, https://github.com/lucas-diedrich/dvp-io
Project-URL: Source, https://github.com/lucas-diedrich/dvp-io
Author: Lucas Diedrich
Maintainer-email: Lucas Diedrich <diedrich@biochem.mpg.de>
License: Apache License Version 2.0
License-File: LICENSE
Classifier: Programming Language :: Python :: 3 :: Only
Classifier: Programming Language :: Python :: 3.10
Classifier: Programming Language :: Python :: 3.11
Classifier: Programming Language :: Python :: 3.12
Requires-Python: <3.13,>=3.10
Requires-Dist: alphabase
Requires-Dist: anndata
Requires-Dist: openslide-bin
Requires-Dist: openslide-python
Requires-Dist: pandas<3
Requires-Dist: py-lmd>=1.3.2
Requires-Dist: pydantic
Requires-Dist: pylibczirw
Requires-Dist: spatialdata>=0.4
Provides-Extra: dev
Requires-Dist: pre-commit; extra == 'dev'
Requires-Dist: twine>=4.0.2; extra == 'dev'
Provides-Extra: doc
Requires-Dist: docutils!=0.18.*,!=0.19.*,>=0.8; extra == 'doc'
Requires-Dist: ipykernel; extra == 'doc'
Requires-Dist: ipython; extra == 'doc'
Requires-Dist: myst-nb>=1.1; extra == 'doc'
Requires-Dist: napari-spatialdata; extra == 'doc'
Requires-Dist: pandas; extra == 'doc'
Requires-Dist: setuptools; extra == 'doc'
Requires-Dist: spatialdata-plot; extra == 'doc'
Requires-Dist: sphinx-autodoc-typehints; extra == 'doc'
Requires-Dist: sphinx-book-theme>=1; extra == 'doc'
Requires-Dist: sphinx-copybutton; extra == 'doc'
Requires-Dist: sphinx-tabs; extra == 'doc'
Requires-Dist: sphinx>=4; extra == 'doc'
Requires-Dist: sphinxcontrib-bibtex>=1; extra == 'doc'
Requires-Dist: sphinxext-opengraph; extra == 'doc'
Provides-Extra: test
Requires-Dist: coverage; extra == 'test'
Requires-Dist: pytest; extra == 'test'
